versed/__init__.py
versed/__main__.py
versed-0.2.0.dist-info/METADATA
versed-0.2.0.dist-info/WHEEL
versed-0.2.0.dist-info/licenses/LICENSE
versed-0.2.0.dist-info/RECORD
