Metadata-Version: 2.3
Name: versed
Version: 0.2.0
Summary: A command line app to aid in scripture memorization. 'I have stored up your word in my heart, that I might not sin against you.' Psalm 119:11
Project-URL: Homepage, https://github.com/josh-spratt/versed
Project-URL: Issues, https://github.com/josh-spratt/versed/issues
Author-email: Josh Spratt <jspratt02@icloud.com>
License-File: LICENSE
Classifier: License :: OSI Approved :: Apache Software License
Classifier: Operating System :: OS Independent
Classifier: Programming Language :: Python :: 3
Requires-Python: >=3.10
